gfs_dynamical_core-0.1.36.dist-info/RECORD
gfs_dynamical_core-0.1.36.dist-info/LICENSE
gfs_dynamical_core-0.1.36.dist-info/WHEEL
gfs_dynamical_core-0.1.36.dist-info/top_level.txt
gfs_dynamical_core-0.1.36.dist-info/METADATA
gfs_dynamical_core/_gfs_dynamics.cpython-39-darwin.so
gfs_dynamical_core/__init__.py
gfs_dynamical_core/component.py
gfs_dynamical_core/.dylibs/libgfortran.5.dylib
gfs_dynamical_core/.dylibs/libquadmath.0.dylib
gfs_dynamical_core/.dylibs/libgomp.1.dylib
